[
  {
    "dates": "2025-01-01",
    "values": -0.16,
    "n_waagen": 1
  },
  {
    "dates": "2025-01-02",
    "values": -0.17,
    "n_waagen": 1
  },
  {
    "dates": "2025-01-03",
    "values": 0.04,
    "n_waagen": 1
  },
  {
    "dates": "2025-01-04",
    "values": -0.38,
    "n_waagen": 1
  },
  {
    "dates": "2025-01-05",
    "values": 0.02,
    "n_waagen": 1
  },
  {
    "dates": "2025-01-06",
    "values": -0.16,
    "n_waagen": 1
  },
  {
    "dates": "2025-01-07",
    "values": -0.14,
    "n_waagen": 1
  },
  {
    "dates": "2025-01-08",
    "values": -0.08,
    "n_waagen": 1
  },
  {
    "dates": "2025-01-09",
    "values": 2.09,
    "n_waagen": 1
  },
  {
    "dates": "2025-01-10",
    "values": 1.91,
    "n_waagen": 1
  },
  {
    "dates": "2025-01-11",
    "values": 1.41,
    "n_waagen": 1
  },
  {
    "dates": "2025-01-12",
    "values": 1.13,
    "n_waagen": 1
  },
  {
    "dates": "2025-01-13",
    "values": 1.08,
    "n_waagen": 1
  },
  {
    "dates": "2025-01-14",
    "values": 0.75,
    "n_waagen": 1
  },
  {
    "dates": "2025-01-15",
    "values": -0.12,
    "n_waagen": 1
  },
  {
    "dates": "2025-01-16",
    "values": -0.17,
    "n_waagen": 1
  },
  {
    "dates": "2025-01-17",
    "values": -0.2,
    "n_waagen": 1
  },
  {
    "dates": "2025-01-18",
    "values": -0.25,
    "n_waagen": 1
  },
  {
    "dates": "2025-01-19",
    "values": -0.29,
    "n_waagen": 1
  },
  {
    "dates": "2025-01-20",
    "values": -0.34,
    "n_waagen": 1
  },
  {
    "dates": "2025-01-21",
    "values": -0.35,
    "n_waagen": 1
  },
  {
    "dates": "2025-01-22",
    "values": -0.34,
    "n_waagen": 1
  },
  {
    "dates": "2025-01-23",
    "values": -0.27,
    "n_waagen": 1
  },
  {
    "dates": "2025-01-24",
    "values": -0.39,
    "n_waagen": 1
  },
  {
    "dates": "2025-01-25",
    "values": -0.41,
    "n_waagen": 1
  },
  {
    "dates": "2025-01-26",
    "values": -0.58,
    "n_waagen": 1
  },
  {
    "dates": "2025-01-27",
    "values": -0.82,
    "n_waagen": 1
  },
  {
    "dates": "2025-01-28",
    "values": -0.92,
    "n_waagen": 1
  },
  {
    "dates": "2025-01-29",
    "values": -1.02,
    "n_waagen": 1
  },
  {
    "dates": "2025-01-30",
    "values": -0.99,
    "n_waagen": 1
  },
  {
    "dates": "2025-01-31",
    "values": -1.06,
    "n_waagen": 1
  },
  {
    "dates": "2025-02-01",
    "values": -1.1,
    "n_waagen": 1
  },
  {
    "dates": "2025-02-02",
    "values": -1.14,
    "n_waagen": 1
  },
  {
    "dates": "2025-02-03",
    "values": -1.18,
    "n_waagen": 1
  },
  {
    "dates": "2025-02-04",
    "values": -1.2,
    "n_waagen": 1
  },
  {
    "dates": "2025-02-05",
    "values": -1.2,
    "n_waagen": 1
  },
  {
    "dates": "2025-02-06",
    "values": -1.25,
    "n_waagen": 1
  },
  {
    "dates": "2025-02-07",
    "values": -1.36,
    "n_waagen": 1
  },
  {
    "dates": "2025-02-08",
    "values": -1.42,
    "n_waagen": 1
  },
  {
    "dates": "2025-02-09",
    "values": -1.49,
    "n_waagen": 1
  },
  {
    "dates": "2025-02-10",
    "values": -1.5,
    "n_waagen": 1
  },
  {
    "dates": "2025-02-11",
    "values": -1.4,
    "n_waagen": 1
  },
  {
    "dates": "2025-02-12",
    "values": -1.39,
    "n_waagen": 1
  },
  {
    "dates": "2025-02-13",
    "values": -1.43,
    "n_waagen": 1
  },
  {
    "dates": "2025-02-14",
    "values": -1.41,
    "n_waagen": 1
  },
  {
    "dates": "2025-02-15",
    "values": -1.42,
    "n_waagen": 1
  },
  {
    "dates": "2025-02-16",
    "values": -1.42,
    "n_waagen": 1
  },
  {
    "dates": "2025-02-17",
    "values": -1.45,
    "n_waagen": 1
  },
  {
    "dates": "2025-02-18",
    "values": -1.47,
    "n_waagen": 1
  },
  {
    "dates": "2025-02-19",
    "values": -1.48,
    "n_waagen": 1
  },
  {
    "dates": "2025-02-20",
    "values": -1.42,
    "n_waagen": 1
  },
  {
    "dates": "2025-02-21",
    "values": -1.67,
    "n_waagen": 1
  },
  {
    "dates": "2025-02-22",
    "values": -1.82,
    "n_waagen": 1
  },
  {
    "dates": "2025-02-23",
    "values": -1.83,
    "n_waagen": 1
  },
  {
    "dates": "2025-02-24",
    "values": -1.87,
    "n_waagen": 1
  },
  {
    "dates": "2025-02-25",
    "values": -1.98,
    "n_waagen": 1
  },
  {
    "dates": "2025-02-26",
    "values": -2.09,
    "n_waagen": 1
  },
  {
    "dates": "2025-02-27",
    "values": -2.12,
    "n_waagen": 1
  },
  {
    "dates": "2025-02-28",
    "values": -2.23,
    "n_waagen": 1
  },
  {
    "dates": "2025-03-01",
    "values": -2.27,
    "n_waagen": 1
  },
  {
    "dates": "2025-03-02",
    "values": -2.26,
    "n_waagen": 1
  },
  {
    "dates": "2025-03-03",
    "values": -2.36,
    "n_waagen": 1
  },
  {
    "dates": "2025-03-04",
    "values": -2.45,
    "n_waagen": 1
  },
  {
    "dates": "2025-03-05",
    "values": -2.7,
    "n_waagen": 1
  },
  {
    "dates": "2025-03-06",
    "values": -2.78,
    "n_waagen": 1
  },
  {
    "dates": "2025-03-07",
    "values": -2.87,
    "n_waagen": 1
  },
  {
    "dates": "2025-03-08",
    "values": -2.95,
    "n_waagen": 1
  },
  {
    "dates": "2025-03-09",
    "values": -3.05,
    "n_waagen": 1
  },
  {
    "dates": "2025-03-10",
    "values": -3.15,
    "n_waagen": 1
  },
  {
    "dates": "2025-03-11",
    "values": -3.25,
    "n_waagen": 1
  },
  {
    "dates": "2025-03-12",
    "values": -3.36,
    "n_waagen": 1
  },
  {
    "dates": "2025-03-13",
    "values": -3.46,
    "n_waagen": 1
  },
  {
    "dates": "2025-03-14",
    "values": -3.51,
    "n_waagen": 1
  },
  {
    "dates": "2025-03-15",
    "values": -3.62,
    "n_waagen": 1
  },
  {
    "dates": "2025-03-16",
    "values": -3.48,
    "n_waagen": 1
  },
  {
    "dates": "2025-03-17",
    "values": -3.66,
    "n_waagen": 1
  },
  {
    "dates": "2025-03-18",
    "values": -3.94,
    "n_waagen": 1
  },
  {
    "dates": "2025-03-19",
    "values": -3.96,
    "n_waagen": 1
  },
  {
    "dates": "2025-03-20",
    "values": -2.66,
    "n_waagen": 1
  },
  {
    "dates": "2025-03-21",
    "values": -1.82,
    "n_waagen": 1
  },
  {
    "dates": "2025-03-22",
    "values": -2.7,
    "n_waagen": 1
  },
  {
    "dates": "2025-03-23",
    "values": -2.3,
    "n_waagen": 1
  },
  {
    "dates": "2025-03-24",
    "values": -3.21,
    "n_waagen": 1
  },
  {
    "dates": "2025-03-25",
    "values": -3.49,
    "n_waagen": 1
  },
  {
    "dates": "2025-03-26",
    "values": -3.56,
    "n_waagen": 1
  },
  {
    "dates": "2025-03-27",
    "values": -3.75,
    "n_waagen": 1
  },
  {
    "dates": "2025-03-28",
    "values": -3.65,
    "n_waagen": 1
  },
  {
    "dates": "2025-03-29",
    "values": -2.74,
    "n_waagen": 1
  },
  {
    "dates": "2025-03-30",
    "values": -2.61,
    "n_waagen": 1
  },
  {
    "dates": "2025-03-31",
    "values": -2.86,
    "n_waagen": 1
  },
  {
    "dates": "2025-04-01",
    "values": -3.03,
    "n_waagen": 1
  },
  {
    "dates": "2025-04-02",
    "values": -3.95,
    "n_waagen": 1
  },
  {
    "dates": "2025-04-03",
    "values": -3.85,
    "n_waagen": 1
  },
  {
    "dates": "2025-04-04",
    "values": -3.58,
    "n_waagen": 1
  },
  {
    "dates": "2025-04-05",
    "values": -3.84,
    "n_waagen": 1
  },
  {
    "dates": "2025-04-06",
    "values": -3.92,
    "n_waagen": 1
  },
  {
    "dates": "2025-04-07",
    "values": -4.17,
    "n_waagen": 1
  },
  {
    "dates": "2025-04-08",
    "values": -4.09,
    "n_waagen": 1
  },
  {
    "dates": "2025-04-09",
    "values": -4.14,
    "n_waagen": 1
  },
  {
    "dates": "2025-04-10",
    "values": -4.95,
    "n_waagen": 1
  },
  {
    "dates": "2025-04-11",
    "values": -3.96,
    "n_waagen": 1
  },
  {
    "dates": "2025-04-12",
    "values": -2.06,
    "n_waagen": 1
  },
  {
    "dates": "2025-04-13",
    "values": -1.06,
    "n_waagen": 1
  },
  {
    "dates": "2025-04-14",
    "values": -0.06,
    "n_waagen": 1
  },
  {
    "dates": "2025-04-15",
    "values": 0.92,
    "n_waagen": 1
  },
  {
    "dates": "2025-04-16",
    "values": 0.43,
    "n_waagen": 1
  },
  {
    "dates": "2025-04-17",
    "values": -0.29,
    "n_waagen": 1
  },
  {
    "dates": "2025-04-18",
    "values": -0.66,
    "n_waagen": 1
  },
  {
    "dates": "2025-04-19",
    "values": -0.01,
    "n_waagen": 1
  },
  {
    "dates": "2025-04-20",
    "values": 1.49,
    "n_waagen": 1
  },
  {
    "dates": "2025-04-21",
    "values": 0.29,
    "n_waagen": 1
  },
  {
    "dates": "2025-04-22",
    "values": 0.53,
    "n_waagen": 1
  },
  {
    "dates": "2025-04-23",
    "values": 0.74,
    "n_waagen": 1
  },
  {
    "dates": "2025-04-24",
    "values": 0.29,
    "n_waagen": 1
  },
  {
    "dates": "2025-04-25",
    "values": 0.27,
    "n_waagen": 1
  },
  {
    "dates": "2025-04-26",
    "values": -0.61,
    "n_waagen": 1
  },
  {
    "dates": "2025-04-27",
    "values": -0.43,
    "n_waagen": 1
  },
  {
    "dates": "2025-04-28",
    "values": 2.39,
    "n_waagen": 1
  },
  {
    "dates": "2025-04-29",
    "values": 3.53,
    "n_waagen": 1
  },
  {
    "dates": "2025-04-30",
    "values": 5.96,
    "n_waagen": 1
  },
  {
    "dates": "2025-05-01",
    "values": 8.27,
    "n_waagen": 1
  },
  {
    "dates": "2025-05-02",
    "values": 9.96,
    "n_waagen": 1
  },
  {
    "dates": "2025-05-03",
    "values": 9.55,
    "n_waagen": 1
  },
  {
    "dates": "2025-05-04",
    "values": 8.95,
    "n_waagen": 1
  },
  {
    "dates": "2025-05-05",
    "values": 8.92,
    "n_waagen": 1
  },
  {
    "dates": "2025-05-06",
    "values": 8.41,
    "n_waagen": 1
  },
  {
    "dates": "2025-05-07",
    "values": 8.25,
    "n_waagen": 1
  },
  {
    "dates": "2025-05-08",
    "values": 8.94,
    "n_waagen": 1
  },
  {
    "dates": "2025-05-09",
    "values": 10.02,
    "n_waagen": 1
  },
  {
    "dates": "2025-05-10",
    "values": 10.81,
    "n_waagen": 1
  },
  {
    "dates": "2025-05-11",
    "values": 11.61,
    "n_waagen": 1
  },
  {
    "dates": "2025-05-12",
    "values": 12.14,
    "n_waagen": 1
  },
  {
    "dates": "2025-05-13",
    "values": 12.49,
    "n_waagen": 1
  },
  {
    "dates": "2025-05-14",
    "values": 12.72,
    "n_waagen": 1
  },
  {
    "dates": "2025-05-15",
    "values": 12.58,
    "n_waagen": 1
  },
  {
    "dates": "2025-05-16",
    "values": 12.58,
    "n_waagen": 1
  },
  {
    "dates": "2025-05-17",
    "values": 13.13,
    "n_waagen": 1
  },
  {
    "dates": "2025-05-18",
    "values": 12.49,
    "n_waagen": 1
  },
  {
    "dates": "2025-05-19",
    "values": 12.56,
    "n_waagen": 1
  },
  {
    "dates": "2025-05-20",
    "values": 13.03,
    "n_waagen": 1
  },
  {
    "dates": "2025-05-21",
    "values": 13.13,
    "n_waagen": 1
  },
  {
    "dates": "2025-05-22",
    "values": 12.88,
    "n_waagen": 1
  },
  {
    "dates": "2025-05-23",
    "values": 12.64,
    "n_waagen": 1
  },
  {
    "dates": "2025-05-24",
    "values": 12.92,
    "n_waagen": 1
  },
  {
    "dates": "2025-05-25",
    "values": 12.78,
    "n_waagen": 1
  },
  {
    "dates": "2025-05-26",
    "values": 13.48,
    "n_waagen": 1
  },
  {
    "dates": "2025-05-27",
    "values": 13.46,
    "n_waagen": 1
  },
  {
    "dates": "2025-05-28",
    "values": 12.98,
    "n_waagen": 1
  },
  {
    "dates": "2025-05-29",
    "values": 12.96,
    "n_waagen": 1
  },
  {
    "dates": "2025-05-30",
    "values": 13.62,
    "n_waagen": 1
  },
  {
    "dates": "2025-05-31",
    "values": 14.26,
    "n_waagen": 1
  },
  {
    "dates": "2025-06-01",
    "values": 14.08,
    "n_waagen": 1
  },
  {
    "dates": "2025-06-02",
    "values": 13.46,
    "n_waagen": 1
  },
  {
    "dates": "2025-06-03",
    "values": 13.53,
    "n_waagen": 1
  },
  {
    "dates": "2025-06-04",
    "values": 13.33,
    "n_waagen": 1
  },
  {
    "dates": "2025-06-05",
    "values": 12.91,
    "n_waagen": 1
  },
  {
    "dates": "2025-06-06",
    "values": 13.06,
    "n_waagen": 1
  },
  {
    "dates": "2025-06-07",
    "values": 12.69,
    "n_waagen": 1
  },
  {
    "dates": "2025-06-08",
    "values": 12.61,
    "n_waagen": 1
  },
  {
    "dates": "2025-06-09",
    "values": 12.53,
    "n_waagen": 1
  },
  {
    "dates": "2025-06-10",
    "values": 12.59,
    "n_waagen": 1
  },
  {
    "dates": "2025-06-11",
    "values": 12.74,
    "n_waagen": 1
  },
  {
    "dates": "2025-06-12",
    "values": 12.87,
    "n_waagen": 1
  },
  {
    "dates": "2025-06-13",
    "values": 13.0,
    "n_waagen": 1
  },
  {
    "dates": "2025-06-14",
    "values": 13.45,
    "n_waagen": 1
  },
  {
    "dates": "2025-06-15",
    "values": 13.32,
    "n_waagen": 1
  },
  {
    "dates": "2025-06-16",
    "values": 13.96,
    "n_waagen": 1
  },
  {
    "dates": "2025-06-17",
    "values": 14.31,
    "n_waagen": 1
  },
  {
    "dates": "2025-06-18",
    "values": 14.59,
    "n_waagen": 1
  },
  {
    "dates": "2025-06-19",
    "values": 14.43,
    "n_waagen": 1
  },
  {
    "dates": "2025-06-20",
    "values": 14.7,
    "n_waagen": 1
  },
  {
    "dates": "2025-06-21",
    "values": 15.23,
    "n_waagen": 1
  },
  {
    "dates": "2025-06-22",
    "values": 15.69,
    "n_waagen": 1
  },
  {
    "dates": "2025-06-23",
    "values": 15.28,
    "n_waagen": 1
  },
  {
    "dates": "2025-06-24",
    "values": 15.63,
    "n_waagen": 1
  },
  {
    "dates": "2025-06-25",
    "values": 15.97,
    "n_waagen": 1
  },
  {
    "dates": "2025-06-26",
    "values": 15.69,
    "n_waagen": 1
  },
  {
    "dates": "2025-06-27",
    "values": 15.59,
    "n_waagen": 1
  },
  {
    "dates": "2025-06-28",
    "values": 16.39,
    "n_waagen": 1
  },
  {
    "dates": "2025-06-29",
    "values": 16.51,
    "n_waagen": 1
  },
  {
    "dates": "2025-06-30",
    "values": 16.21,
    "n_waagen": 1
  },
  {
    "dates": "2025-07-01",
    "values": 16.32,
    "n_waagen": 1
  },
  {
    "dates": "2025-07-02",
    "values": 16.69,
    "n_waagen": 1
  },
  {
    "dates": "2025-07-03",
    "values": 16.6,
    "n_waagen": 1
  },
  {
    "dates": "2025-07-04",
    "values": 16.49,
    "n_waagen": 1
  },
  {
    "dates": "2025-07-05",
    "values": 16.53,
    "n_waagen": 1
  },
  {
    "dates": "2025-07-06",
    "values": 16.06,
    "n_waagen": 1
  },
  {
    "dates": "2025-07-07",
    "values": 16.25,
    "n_waagen": 1
  },
  {
    "dates": "2025-07-08",
    "values": 15.93,
    "n_waagen": 1
  },
  {
    "dates": "2025-07-09",
    "values": 15.78,
    "n_waagen": 1
  },
  {
    "dates": "2025-07-10",
    "values": 15.52,
    "n_waagen": 1
  },
  {
    "dates": "2025-07-11",
    "values": 15.51,
    "n_waagen": 1
  },
  {
    "dates": "2025-07-12",
    "values": 15.29,
    "n_waagen": 1
  },
  {
    "dates": "2025-07-13",
    "values": 15.43,
    "n_waagen": 1
  },
  {
    "dates": "2025-07-14",
    "values": 15.56,
    "n_waagen": 1
  },
  {
    "dates": "2025-07-15",
    "values": 15.56,
    "n_waagen": 1
  },
  {
    "dates": "2025-07-16",
    "values": 15.87,
    "n_waagen": 1
  },
  {
    "dates": "2025-07-17",
    "values": 15.74,
    "n_waagen": 1
  },
  {
    "dates": "2025-07-18",
    "values": 15.82,
    "n_waagen": 1
  },
  {
    "dates": "2025-07-19",
    "values": 15.8,
    "n_waagen": 1
  },
  {
    "dates": "2025-07-20",
    "values": 15.81,
    "n_waagen": 1
  },
  {
    "dates": "2025-07-21",
    "values": 15.81,
    "n_waagen": 1
  },
  {
    "dates": "2025-07-22",
    "values": 16.18,
    "n_waagen": 1
  },
  {
    "dates": "2025-07-23",
    "values": 15.79,
    "n_waagen": 1
  },
  {
    "dates": "2025-07-24",
    "values": 15.71,
    "n_waagen": 1
  },
  {
    "dates": "2025-07-25",
    "values": 15.66,
    "n_waagen": 1
  },
  {
    "dates": "2025-07-26",
    "values": 15.22,
    "n_waagen": 1
  },
  {
    "dates": "2025-07-27",
    "values": 15.26,
    "n_waagen": 1
  },
  {
    "dates": "2025-07-28",
    "values": 15.13,
    "n_waagen": 1
  },
  {
    "dates": "2025-07-29",
    "values": 14.81,
    "n_waagen": 1
  },
  {
    "dates": "2025-07-30",
    "values": 14.88,
    "n_waagen": 1
  },
  {
    "dates": "2025-07-31",
    "values": 14.8,
    "n_waagen": 1
  },
  {
    "dates": "2025-08-01",
    "values": 14.87,
    "n_waagen": 1
  },
  {
    "dates": "2025-08-02",
    "values": 14.73,
    "n_waagen": 1
  },
  {
    "dates": "2025-08-03",
    "values": 14.53,
    "n_waagen": 1
  },
  {
    "dates": "2025-08-04",
    "values": 14.49,
    "n_waagen": 1
  },
  {
    "dates": "2025-08-05",
    "values": 14.27,
    "n_waagen": 1
  },
  {
    "dates": "2025-08-06",
    "values": 14.06,
    "n_waagen": 1
  },
  {
    "dates": "2025-08-07",
    "values": 13.95,
    "n_waagen": 1
  },
  {
    "dates": "2025-08-08",
    "values": 13.87,
    "n_waagen": 1
  },
  {
    "dates": "2025-08-09",
    "values": 13.75,
    "n_waagen": 1
  },
  {
    "dates": "2025-08-10",
    "values": 13.63,
    "n_waagen": 1
  },
  {
    "dates": "2025-08-11",
    "values": 13.73,
    "n_waagen": 1
  },
  {
    "dates": "2025-08-12",
    "values": 13.82,
    "n_waagen": 1
  },
  {
    "dates": "2025-08-13",
    "values": 14.4,
    "n_waagen": 1
  },
  {
    "dates": "2025-08-14",
    "values": 14.8,
    "n_waagen": 1
  },
  {
    "dates": "2025-08-15",
    "values": 15.01,
    "n_waagen": 1
  },
  {
    "dates": "2025-08-16",
    "values": 15.79,
    "n_waagen": 1
  },
  {
    "dates": "2025-08-17",
    "values": 15.78,
    "n_waagen": 1
  },
  {
    "dates": "2025-08-18",
    "values": 15.66,
    "n_waagen": 1
  },
  {
    "dates": "2025-08-19",
    "values": 15.68,
    "n_waagen": 1
  },
  {
    "dates": "2025-08-20",
    "values": 15.37,
    "n_waagen": 1
  },
  {
    "dates": "2025-08-21",
    "values": 15.13,
    "n_waagen": 1
  },
  {
    "dates": "2025-08-22",
    "values": 14.96,
    "n_waagen": 1
  },
  {
    "dates": "2025-08-23",
    "values": 14.78,
    "n_waagen": 1
  },
  {
    "dates": "2025-08-24",
    "values": 14.53,
    "n_waagen": 1
  },
  {
    "dates": "2025-08-25",
    "values": 14.41,
    "n_waagen": 1
  },
  {
    "dates": "2025-08-26",
    "values": 14.27,
    "n_waagen": 1
  },
  {
    "dates": "2025-08-27",
    "values": 14.17,
    "n_waagen": 1
  },
  {
    "dates": "2025-08-28",
    "values": 14.01,
    "n_waagen": 1
  },
  {
    "dates": "2025-08-29",
    "values": 14.01,
    "n_waagen": 1
  },
  {
    "dates": "2025-08-30",
    "values": 13.9,
    "n_waagen": 1
  },
  {
    "dates": "2025-08-31",
    "values": 13.73,
    "n_waagen": 1
  },
  {
    "dates": "2025-09-01",
    "values": 13.72,
    "n_waagen": 1
  },
  {
    "dates": "2025-09-02",
    "values": 13.55,
    "n_waagen": 1
  },
  {
    "dates": "2025-09-03",
    "values": 13.69,
    "n_waagen": 1
  },
  {
    "dates": "2025-09-04",
    "values": 13.6,
    "n_waagen": 1
  },
  {
    "dates": "2025-09-05",
    "values": 13.45,
    "n_waagen": 1
  },
  {
    "dates": "2025-09-06",
    "values": 13.42,
    "n_waagen": 1
  },
  {
    "dates": "2025-09-07",
    "values": 13.35,
    "n_waagen": 1
  },
  {
    "dates": "2025-09-08",
    "values": 13.44,
    "n_waagen": 1
  },
  {
    "dates": "2025-09-09",
    "values": 13.39,
    "n_waagen": 1
  },
  {
    "dates": "2025-09-10",
    "values": 13.21,
    "n_waagen": 1
  },
  {
    "dates": "2025-09-11",
    "values": 13.05,
    "n_waagen": 1
  },
  {
    "dates": "2025-09-12",
    "values": 13.01,
    "n_waagen": 1
  },
  {
    "dates": "2025-09-13",
    "values": 13.23,
    "n_waagen": 1
  },
  {
    "dates": "2025-09-14",
    "values": 13.04,
    "n_waagen": 1
  },
  {
    "dates": "2025-09-15",
    "values": 12.64,
    "n_waagen": 1
  },
  {
    "dates": "2025-09-16",
    "values": 12.69,
    "n_waagen": 1
  },
  {
    "dates": "2025-09-17",
    "values": 12.63,
    "n_waagen": 1
  },
  {
    "dates": "2025-09-18",
    "values": 12.45,
    "n_waagen": 1
  },
  {
    "dates": "2025-09-19",
    "values": 12.4,
    "n_waagen": 1
  },
  {
    "dates": "2025-09-20",
    "values": 12.39,
    "n_waagen": 1
  },
  {
    "dates": "2025-09-21",
    "values": 12.3,
    "n_waagen": 1
  },
  {
    "dates": "2025-09-22",
    "values": 12.32,
    "n_waagen": 1
  },
  {
    "dates": "2025-09-23",
    "values": 12.31,
    "n_waagen": 1
  },
  {
    "dates": "2025-09-24",
    "values": 12.15,
    "n_waagen": 1
  },
  {
    "dates": "2025-09-25",
    "values": 12.12,
    "n_waagen": 1
  },
  {
    "dates": "2025-09-26",
    "values": 12.13,
    "n_waagen": 1
  },
  {
    "dates": "2025-09-27",
    "values": 12.06,
    "n_waagen": 1
  },
  {
    "dates": "2025-09-28",
    "values": 11.95,
    "n_waagen": 1
  },
  {
    "dates": "2025-09-29",
    "values": 11.89,
    "n_waagen": 1
  },
  {
    "dates": "2025-09-30",
    "values": 11.77,
    "n_waagen": 1
  },
  {
    "dates": "2025-10-01",
    "values": 11.75,
    "n_waagen": 1
  },
  {
    "dates": "2025-10-02",
    "values": 11.65,
    "n_waagen": 1
  },
  {
    "dates": "2025-10-03",
    "values": 11.62,
    "n_waagen": 1
  },
  {
    "dates": "2025-10-04",
    "values": 11.8,
    "n_waagen": 1
  },
  {
    "dates": "2025-10-05",
    "values": 11.83,
    "n_waagen": 1
  },
  {
    "dates": "2025-10-06",
    "values": 11.92,
    "n_waagen": 1
  },
  {
    "dates": "2025-10-07",
    "values": 11.92,
    "n_waagen": 1
  },
  {
    "dates": "2025-10-08",
    "values": 11.78,
    "n_waagen": 1
  },
  {
    "dates": "2025-10-09",
    "values": 11.68,
    "n_waagen": 1
  },
  {
    "dates": "2025-10-10",
    "values": 11.54,
    "n_waagen": 1
  },
  {
    "dates": "2025-10-11",
    "values": 11.5,
    "n_waagen": 1
  },
  {
    "dates": "2025-10-12",
    "values": 11.52,
    "n_waagen": 1
  },
  {
    "dates": "2025-10-13",
    "values": 11.52,
    "n_waagen": 1
  },
  {
    "dates": "2025-10-14",
    "values": 11.55,
    "n_waagen": 1
  },
  {
    "dates": "2025-10-15",
    "values": 11.65,
    "n_waagen": 1
  },
  {
    "dates": "2025-10-16",
    "values": 11.69,
    "n_waagen": 1
  },
  {
    "dates": "2025-10-17",
    "values": 11.57,
    "n_waagen": 1
  },
  {
    "dates": "2025-10-18",
    "values": 11.49,
    "n_waagen": 1
  },
  {
    "dates": "2025-10-19",
    "values": 11.5,
    "n_waagen": 1
  },
  {
    "dates": "2025-10-20",
    "values": 11.51,
    "n_waagen": 1
  },
  {
    "dates": "2025-10-21",
    "values": 11.65,
    "n_waagen": 1
  },
  {
    "dates": "2025-10-22",
    "values": 11.56,
    "n_waagen": 1
  },
  {
    "dates": "2025-10-23",
    "values": 11.47,
    "n_waagen": 1
  },
  {
    "dates": "2025-10-24",
    "values": 11.44,
    "n_waagen": 1
  },
  {
    "dates": "2025-10-25",
    "values": 11.5,
    "n_waagen": 1
  },
  {
    "dates": "2025-10-26",
    "values": 11.39,
    "n_waagen": 1
  },
  {
    "dates": "2025-10-27",
    "values": 11.58,
    "n_waagen": 1
  },
  {
    "dates": "2025-10-28",
    "values": 11.53,
    "n_waagen": 1
  },
  {
    "dates": "2025-10-29",
    "values": 11.39,
    "n_waagen": 1
  },
  {
    "dates": "2025-10-30",
    "values": 11.34,
    "n_waagen": 1
  },
  {
    "dates": "2025-10-31",
    "values": 11.28,
    "n_waagen": 1
  },
  {
    "dates": "2025-11-01",
    "values": 11.33,
    "n_waagen": 1
  },
  {
    "dates": "2025-11-02",
    "values": 11.38,
    "n_waagen": 1
  },
  {
    "dates": "2025-11-03",
    "values": 11.31,
    "n_waagen": 1
  },
  {
    "dates": "2025-11-04",
    "values": 13.08,
    "n_waagen": 1
  },
  {
    "dates": "2025-11-05",
    "values": 14.26,
    "n_waagen": 1
  },
  {
    "dates": "2025-11-06",
    "values": 15.02,
    "n_waagen": 1
  },
  {
    "dates": "2025-11-07",
    "values": 14.89,
    "n_waagen": 1
  },
  {
    "dates": "2025-11-08",
    "values": 15.17,
    "n_waagen": 1
  },
  {
    "dates": "2025-11-09",
    "values": 15.57,
    "n_waagen": 1
  },
  {
    "dates": "2025-11-10",
    "values": 15.43,
    "n_waagen": 1
  },
  {
    "dates": "2025-11-11",
    "values": 15.48,
    "n_waagen": 1
  },
  {
    "dates": "2025-11-12",
    "values": 15.41,
    "n_waagen": 1
  },
  {
    "dates": "2025-11-13",
    "values": 15.29,
    "n_waagen": 1
  },
  {
    "dates": "2025-11-14",
    "values": 15.32,
    "n_waagen": 1
  },
  {
    "dates": "2025-11-15",
    "values": 15.3,
    "n_waagen": 1
  },
  {
    "dates": "2025-11-16",
    "values": 15.31,
    "n_waagen": 1
  },
  {
    "dates": "2025-11-17",
    "values": 15.2,
    "n_waagen": 1
  },
  {
    "dates": "2025-11-18",
    "values": 16.21,
    "n_waagen": 1
  },
  {
    "dates": "2025-11-19",
    "values": 15.7,
    "n_waagen": 1
  },
  {
    "dates": "2025-11-20",
    "values": 15.98,
    "n_waagen": 1
  },
  {
    "dates": "2025-11-21",
    "values": 15.9,
    "n_waagen": 1
  },
  {
    "dates": "2025-11-22",
    "values": 15.81,
    "n_waagen": 1
  },
  {
    "dates": "2025-11-23",
    "values": 16.07,
    "n_waagen": 1
  },
  {
    "dates": "2025-11-24",
    "values": 15.9,
    "n_waagen": 1
  },
  {
    "dates": "2025-11-25",
    "values": 15.84,
    "n_waagen": 1
  },
  {
    "dates": "2025-11-26",
    "values": 15.8,
    "n_waagen": 1
  },
  {
    "dates": "2025-11-27",
    "values": 15.76,
    "n_waagen": 1
  },
  {
    "dates": "2025-11-28",
    "values": 15.78,
    "n_waagen": 1
  },
  {
    "dates": "2025-11-29",
    "values": 15.74,
    "n_waagen": 1
  },
  {
    "dates": "2025-11-30",
    "values": 15.74,
    "n_waagen": 1
  },
  {
    "dates": "2025-12-01",
    "values": 15.69,
    "n_waagen": 1
  },
  {
    "dates": "2025-12-02",
    "values": 15.72,
    "n_waagen": 1
  },
  {
    "dates": "2025-12-03",
    "values": 15.63,
    "n_waagen": 1
  },
  {
    "dates": "2025-12-04",
    "values": 15.59,
    "n_waagen": 1
  },
  {
    "dates": "2025-12-05",
    "values": 15.58,
    "n_waagen": 1
  },
  {
    "dates": "2025-12-06",
    "values": 15.43,
    "n_waagen": 1
  },
  {
    "dates": "2025-12-07",
    "values": 15.47,
    "n_waagen": 1
  },
  {
    "dates": "2025-12-08",
    "values": 15.36,
    "n_waagen": 1
  },
  {
    "dates": "2025-12-09",
    "values": 15.3,
    "n_waagen": 1
  },
  {
    "dates": "2025-12-10",
    "values": 15.25,
    "n_waagen": 1
  },
  {
    "dates": "2025-12-11",
    "values": 15.27,
    "n_waagen": 1
  },
  {
    "dates": "2025-12-12",
    "values": 15.27,
    "n_waagen": 1
  },
  {
    "dates": "2025-12-13",
    "values": 15.24,
    "n_waagen": 1
  },
  {
    "dates": "2025-12-14",
    "values": 15.2,
    "n_waagen": 1
  },
  {
    "dates": "2025-12-15",
    "values": 15.15,
    "n_waagen": 1
  },
  {
    "dates": "2025-12-16",
    "values": 15.14,
    "n_waagen": 1
  },
  {
    "dates": "2025-12-17",
    "values": 15.12,
    "n_waagen": 1
  },
  {
    "dates": "2025-12-18",
    "values": 15.1,
    "n_waagen": 1
  },
  {
    "dates": "2025-12-19",
    "values": 15.04,
    "n_waagen": 1
  },
  {
    "dates": "2025-12-20",
    "values": 15.03,
    "n_waagen": 1
  },
  {
    "dates": "2025-12-21",
    "values": 14.99,
    "n_waagen": 1
  },
  {
    "dates": "2025-12-22",
    "values": 14.92,
    "n_waagen": 1
  },
  {
    "dates": "2025-12-23",
    "values": 14.81,
    "n_waagen": 1
  },
  {
    "dates": "2025-12-24",
    "values": 14.79,
    "n_waagen": 1
  },
  {
    "dates": "2025-12-25",
    "values": 14.77,
    "n_waagen": 1
  },
  {
    "dates": "2025-12-26",
    "values": 14.73,
    "n_waagen": 1
  },
  {
    "dates": "2025-12-27",
    "values": 14.76,
    "n_waagen": 1
  },
  {
    "dates": "2025-12-28",
    "values": 14.74,
    "n_waagen": 1
  },
  {
    "dates": "2025-12-29",
    "values": 14.72,
    "n_waagen": 1
  },
  {
    "dates": "2025-12-30",
    "values": 14.72,
    "n_waagen": 1
  }
]
