[
  {
    "dates": "2026-01-01",
    "values": 0.94,
    "n_waagen": 1
  },
  {
    "dates": "2026-01-02",
    "values": 1.67,
    "n_waagen": 1
  },
  {
    "dates": "2026-01-03",
    "values": 1.84,
    "n_waagen": 1
  },
  {
    "dates": "2026-01-04",
    "values": 3.27,
    "n_waagen": 1
  },
  {
    "dates": "2026-01-05",
    "values": 4.36,
    "n_waagen": 1
  },
  {
    "dates": "2026-01-06",
    "values": null,
    "n_waagen": null
  },
  {
    "dates": "2026-01-07",
    "values": null,
    "n_waagen": null
  },
  {
    "dates": "2026-01-08",
    "values": 5.06,
    "n_waagen": 1
  },
  {
    "dates": "2026-01-09",
    "values": 3.03,
    "n_waagen": 1
  },
  {
    "dates": "2026-01-10",
    "values": 2.92,
    "n_waagen": 1
  },
  {
    "dates": "2026-01-11",
    "values": 2.62,
    "n_waagen": 1
  },
  {
    "dates": "2026-01-12",
    "values": 2.37,
    "n_waagen": 1
  },
  {
    "dates": "2026-01-13",
    "values": 1.85,
    "n_waagen": 1
  },
  {
    "dates": "2026-01-14",
    "values": 1.82,
    "n_waagen": 1
  },
  {
    "dates": "2026-01-15",
    "values": 1.6,
    "n_waagen": 1
  },
  {
    "dates": "2026-01-16",
    "values": 1.25,
    "n_waagen": 1
  },
  {
    "dates": "2026-01-17",
    "values": 1.18,
    "n_waagen": 1
  },
  {
    "dates": "2026-01-18",
    "values": 1.15,
    "n_waagen": 1
  },
  {
    "dates": "2026-01-19",
    "values": 0.97,
    "n_waagen": 1
  },
  {
    "dates": "2026-01-20",
    "values": 0.79,
    "n_waagen": 1
  },
  {
    "dates": "2026-01-21",
    "values": 0.66,
    "n_waagen": 1
  },
  {
    "dates": "2026-01-22",
    "values": 0.56,
    "n_waagen": 1
  },
  {
    "dates": "2026-01-23",
    "values": 0.46,
    "n_waagen": 1
  },
  {
    "dates": "2026-01-24",
    "values": 0.36,
    "n_waagen": 1
  },
  {
    "dates": "2026-01-25",
    "values": 0.43,
    "n_waagen": 1
  },
  {
    "dates": "2026-01-26",
    "values": 2.14,
    "n_waagen": 1
  },
  {
    "dates": "2026-01-27",
    "values": 2.35,
    "n_waagen": 1
  },
  {
    "dates": "2026-01-28",
    "values": 2.56,
    "n_waagen": 1
  },
  {
    "dates": "2026-01-29",
    "values": 4.59,
    "n_waagen": 1
  },
  {
    "dates": "2026-01-30",
    "values": 3.93,
    "n_waagen": 1
  },
  {
    "dates": "2026-01-31",
    "values": 2.46,
    "n_waagen": 1
  },
  {
    "dates": "2026-02-01",
    "values": 0.49,
    "n_waagen": 1
  },
  {
    "dates": "2026-02-02",
    "values": -0.03,
    "n_waagen": 1
  },
  {
    "dates": "2026-02-03",
    "values": 2.19,
    "n_waagen": 1
  },
  {
    "dates": "2026-02-04",
    "values": 1.7,
    "n_waagen": 1
  },
  {
    "dates": "2026-02-05",
    "values": 1.04,
    "n_waagen": 1
  },
  {
    "dates": "2026-02-06",
    "values": 0.98,
    "n_waagen": 1
  },
  {
    "dates": "2026-02-07",
    "values": 0.72,
    "n_waagen": 1
  },
  {
    "dates": "2026-02-08",
    "values": 0.59,
    "n_waagen": 1
  },
  {
    "dates": "2026-02-09",
    "values": 0.44,
    "n_waagen": 1
  },
  {
    "dates": "2026-02-10",
    "values": 0.63,
    "n_waagen": 1
  },
  {
    "dates": "2026-02-11",
    "values": 0.6,
    "n_waagen": 1
  },
  {
    "dates": "2026-02-12",
    "values": 0.6,
    "n_waagen": 1
  },
  {
    "dates": "2026-02-13",
    "values": 0.34,
    "n_waagen": 1
  },
  {
    "dates": "2026-02-14",
    "values": 0.24,
    "n_waagen": 1
  },
  {
    "dates": "2026-02-15",
    "values": 1.24,
    "n_waagen": 1
  },
  {
    "dates": "2026-02-16",
    "values": 0.09,
    "n_waagen": 1
  },
  {
    "dates": "2026-02-17",
    "values": -0.11,
    "n_waagen": 1
  },
  {
    "dates": "2026-02-18",
    "values": -0.36,
    "n_waagen": 1
  },
  {
    "dates": "2026-02-19",
    "values": -0.44,
    "n_waagen": 1
  },
  {
    "dates": "2026-02-20",
    "values": null,
    "n_waagen": null
  },
  {
    "dates": "2026-02-21",
    "values": null,
    "n_waagen": null
  },
  {
    "dates": "2026-02-22",
    "values": null,
    "n_waagen": null
  },
  {
    "dates": "2026-02-23",
    "values": null,
    "n_waagen": null
  },
  {
    "dates": "2026-02-24",
    "values": null,
    "n_waagen": null
  },
  {
    "dates": "2026-02-25",
    "values": null,
    "n_waagen": null
  },
  {
    "dates": "2026-02-26",
    "values": null,
    "n_waagen": null
  },
  {
    "dates": "2026-02-27",
    "values": null,
    "n_waagen": null
  },
  {
    "dates": "2026-02-28",
    "values": null,
    "n_waagen": null
  }
]
