[
  {
    "dates": "2025-01-01",
    "values": -0.11,
    "n_waagen": 2
  },
  {
    "dates": "2025-01-02",
    "values": 0.08,
    "n_waagen": 2
  },
  {
    "dates": "2025-01-03",
    "values": -0.18,
    "n_waagen": 2
  },
  {
    "dates": "2025-01-04",
    "values": 0.13,
    "n_waagen": 2
  },
  {
    "dates": "2025-01-05",
    "values": 0.16,
    "n_waagen": 2
  },
  {
    "dates": "2025-01-06",
    "values": 0.13,
    "n_waagen": 2
  },
  {
    "dates": "2025-01-07",
    "values": 0.23,
    "n_waagen": 2
  },
  {
    "dates": "2025-01-08",
    "values": 0.33,
    "n_waagen": 2
  },
  {
    "dates": "2025-01-09",
    "values": 0.62,
    "n_waagen": 2
  },
  {
    "dates": "2025-01-10",
    "values": 0.51,
    "n_waagen": 2
  },
  {
    "dates": "2025-01-11",
    "values": 0.11,
    "n_waagen": 2
  },
  {
    "dates": "2025-01-12",
    "values": 0.44,
    "n_waagen": 2
  },
  {
    "dates": "2025-01-13",
    "values": 0.16,
    "n_waagen": 2
  },
  {
    "dates": "2025-01-14",
    "values": -0.54,
    "n_waagen": 2
  },
  {
    "dates": "2025-01-15",
    "values": -0.83,
    "n_waagen": 2
  },
  {
    "dates": "2025-01-16",
    "values": -0.87,
    "n_waagen": 2
  },
  {
    "dates": "2025-01-17",
    "values": -0.92,
    "n_waagen": 2
  },
  {
    "dates": "2025-01-18",
    "values": -0.99,
    "n_waagen": 2
  },
  {
    "dates": "2025-01-19",
    "values": -0.78,
    "n_waagen": 2
  },
  {
    "dates": "2025-01-20",
    "values": -1.06,
    "n_waagen": 2
  },
  {
    "dates": "2025-01-21",
    "values": -0.51,
    "n_waagen": 2
  },
  {
    "dates": "2025-01-22",
    "values": -0.91,
    "n_waagen": 2
  },
  {
    "dates": "2025-01-23",
    "values": -0.66,
    "n_waagen": 2
  },
  {
    "dates": "2025-01-24",
    "values": -0.86,
    "n_waagen": 2
  },
  {
    "dates": "2025-01-25",
    "values": -1.51,
    "n_waagen": 2
  },
  {
    "dates": "2025-01-26",
    "values": -1.04,
    "n_waagen": 2
  },
  {
    "dates": "2025-01-27",
    "values": -1.0,
    "n_waagen": 2
  },
  {
    "dates": "2025-01-28",
    "values": -0.96,
    "n_waagen": 2
  },
  {
    "dates": "2025-01-29",
    "values": -1.17,
    "n_waagen": 2
  },
  {
    "dates": "2025-01-30",
    "values": -1.17,
    "n_waagen": 2
  },
  {
    "dates": "2025-01-31",
    "values": -1.21,
    "n_waagen": 2
  },
  {
    "dates": "2025-02-01",
    "values": -1.3,
    "n_waagen": 2
  },
  {
    "dates": "2025-02-02",
    "values": -1.31,
    "n_waagen": 2
  },
  {
    "dates": "2025-02-03",
    "values": -1.3,
    "n_waagen": 2
  },
  {
    "dates": "2025-02-04",
    "values": -1.41,
    "n_waagen": 2
  },
  {
    "dates": "2025-02-05",
    "values": -1.43,
    "n_waagen": 2
  },
  {
    "dates": "2025-02-06",
    "values": -1.33,
    "n_waagen": 2
  },
  {
    "dates": "2025-02-07",
    "values": -1.52,
    "n_waagen": 2
  },
  {
    "dates": "2025-02-08",
    "values": -1.59,
    "n_waagen": 2
  },
  {
    "dates": "2025-02-09",
    "values": -1.57,
    "n_waagen": 2
  },
  {
    "dates": "2025-02-10",
    "values": -1.64,
    "n_waagen": 2
  },
  {
    "dates": "2025-02-11",
    "values": -1.65,
    "n_waagen": 2
  },
  {
    "dates": "2025-02-12",
    "values": -1.78,
    "n_waagen": 2
  },
  {
    "dates": "2025-02-13",
    "values": -2.01,
    "n_waagen": 2
  },
  {
    "dates": "2025-02-14",
    "values": -2.11,
    "n_waagen": 2
  },
  {
    "dates": "2025-02-15",
    "values": -2.06,
    "n_waagen": 2
  },
  {
    "dates": "2025-02-16",
    "values": -2.1,
    "n_waagen": 2
  },
  {
    "dates": "2025-02-17",
    "values": -2.15,
    "n_waagen": 2
  },
  {
    "dates": "2025-02-18",
    "values": -2.26,
    "n_waagen": 2
  },
  {
    "dates": "2025-02-19",
    "values": -2.33,
    "n_waagen": 2
  },
  {
    "dates": "2025-02-20",
    "values": -2.41,
    "n_waagen": 2
  },
  {
    "dates": "2025-02-21",
    "values": -2.63,
    "n_waagen": 2
  },
  {
    "dates": "2025-02-22",
    "values": -2.8,
    "n_waagen": 2
  },
  {
    "dates": "2025-02-23",
    "values": -2.89,
    "n_waagen": 2
  },
  {
    "dates": "2025-02-24",
    "values": -2.86,
    "n_waagen": 2
  },
  {
    "dates": "2025-02-25",
    "values": -2.9,
    "n_waagen": 2
  },
  {
    "dates": "2025-02-26",
    "values": -2.99,
    "n_waagen": 2
  },
  {
    "dates": "2025-02-27",
    "values": -3.11,
    "n_waagen": 2
  },
  {
    "dates": "2025-02-28",
    "values": -3.15,
    "n_waagen": 2
  },
  {
    "dates": "2025-03-01",
    "values": -3.25,
    "n_waagen": 2
  },
  {
    "dates": "2025-03-02",
    "values": -3.27,
    "n_waagen": 2
  },
  {
    "dates": "2025-03-03",
    "values": -3.47,
    "n_waagen": 2
  },
  {
    "dates": "2025-03-04",
    "values": -3.6,
    "n_waagen": 2
  },
  {
    "dates": "2025-03-05",
    "values": -3.75,
    "n_waagen": 2
  },
  {
    "dates": "2025-03-06",
    "values": -3.82,
    "n_waagen": 2
  },
  {
    "dates": "2025-03-07",
    "values": -3.89,
    "n_waagen": 2
  },
  {
    "dates": "2025-03-08",
    "values": -4.06,
    "n_waagen": 2
  },
  {
    "dates": "2025-03-09",
    "values": -4.28,
    "n_waagen": 2
  },
  {
    "dates": "2025-03-10",
    "values": -4.36,
    "n_waagen": 2
  },
  {
    "dates": "2025-03-11",
    "values": -4.34,
    "n_waagen": 2
  },
  {
    "dates": "2025-03-12",
    "values": -4.41,
    "n_waagen": 2
  },
  {
    "dates": "2025-03-13",
    "values": -4.49,
    "n_waagen": 2
  },
  {
    "dates": "2025-03-14",
    "values": -4.61,
    "n_waagen": 2
  },
  {
    "dates": "2025-03-15",
    "values": -4.73,
    "n_waagen": 2
  },
  {
    "dates": "2025-03-16",
    "values": -4.92,
    "n_waagen": 2
  },
  {
    "dates": "2025-03-17",
    "values": -4.93,
    "n_waagen": 2
  },
  {
    "dates": "2025-03-18",
    "values": -5.1,
    "n_waagen": 2
  },
  {
    "dates": "2025-03-19",
    "values": -4.88,
    "n_waagen": 2
  },
  {
    "dates": "2025-03-20",
    "values": -4.65,
    "n_waagen": 2
  },
  {
    "dates": "2025-03-21",
    "values": -3.98,
    "n_waagen": 2
  },
  {
    "dates": "2025-03-22",
    "values": -3.42,
    "n_waagen": 2
  },
  {
    "dates": "2025-03-23",
    "values": -3.48,
    "n_waagen": 2
  },
  {
    "dates": "2025-03-24",
    "values": -3.36,
    "n_waagen": 2
  },
  {
    "dates": "2025-03-25",
    "values": -3.41,
    "n_waagen": 2
  },
  {
    "dates": "2025-03-26",
    "values": -3.43,
    "n_waagen": 2
  },
  {
    "dates": "2025-03-27",
    "values": null,
    "n_waagen": null
  },
  {
    "dates": "2025-03-28",
    "values": -3.44,
    "n_waagen": 2
  },
  {
    "dates": "2025-03-29",
    "values": -3.59,
    "n_waagen": 2
  },
  {
    "dates": "2025-03-30",
    "values": -3.73,
    "n_waagen": 2
  },
  {
    "dates": "2025-03-31",
    "values": -3.87,
    "n_waagen": 2
  },
  {
    "dates": "2025-04-01",
    "values": -4.0,
    "n_waagen": 2
  },
  {
    "dates": "2025-04-02",
    "values": -4.05,
    "n_waagen": 2
  },
  {
    "dates": "2025-04-03",
    "values": -4.04,
    "n_waagen": 2
  },
  {
    "dates": "2025-04-04",
    "values": -4.09,
    "n_waagen": 2
  },
  {
    "dates": "2025-04-05",
    "values": -4.01,
    "n_waagen": 2
  },
  {
    "dates": "2025-04-06",
    "values": -4.28,
    "n_waagen": 2
  },
  {
    "dates": "2025-04-07",
    "values": -4.39,
    "n_waagen": 2
  },
  {
    "dates": "2025-04-08",
    "values": -4.4,
    "n_waagen": 2
  },
  {
    "dates": "2025-04-09",
    "values": -4.29,
    "n_waagen": 2
  },
  {
    "dates": "2025-04-10",
    "values": -4.09,
    "n_waagen": 2
  },
  {
    "dates": "2025-04-11",
    "values": -3.76,
    "n_waagen": 2
  },
  {
    "dates": "2025-04-12",
    "values": -3.39,
    "n_waagen": 2
  },
  {
    "dates": "2025-04-13",
    "values": -3.16,
    "n_waagen": 2
  },
  {
    "dates": "2025-04-14",
    "values": -2.0,
    "n_waagen": 2
  },
  {
    "dates": "2025-04-15",
    "values": -0.4,
    "n_waagen": 2
  },
  {
    "dates": "2025-04-16",
    "values": 0.95,
    "n_waagen": 2
  },
  {
    "dates": "2025-04-17",
    "values": 0.34,
    "n_waagen": 2
  },
  {
    "dates": "2025-04-18",
    "values": -0.03,
    "n_waagen": 2
  },
  {
    "dates": "2025-04-19",
    "values": 1.81,
    "n_waagen": 2
  },
  {
    "dates": "2025-04-20",
    "values": 2.64,
    "n_waagen": 2
  },
  {
    "dates": "2025-04-21",
    "values": 3.84,
    "n_waagen": 2
  },
  {
    "dates": "2025-04-22",
    "values": 4.94,
    "n_waagen": 2
  },
  {
    "dates": "2025-04-23",
    "values": 6.6,
    "n_waagen": 2
  },
  {
    "dates": "2025-04-24",
    "values": 6.11,
    "n_waagen": 2
  },
  {
    "dates": "2025-04-25",
    "values": 5.78,
    "n_waagen": 2
  },
  {
    "dates": "2025-04-26",
    "values": 5.35,
    "n_waagen": 2
  },
  {
    "dates": "2025-04-27",
    "values": 6.28,
    "n_waagen": 2
  },
  {
    "dates": "2025-04-28",
    "values": 7.74,
    "n_waagen": 2
  },
  {
    "dates": "2025-04-29",
    "values": 8.55,
    "n_waagen": 2
  },
  {
    "dates": "2025-04-30",
    "values": 8.99,
    "n_waagen": 2
  },
  {
    "dates": "2025-05-01",
    "values": 9.26,
    "n_waagen": 2
  },
  {
    "dates": "2025-05-02",
    "values": 9.64,
    "n_waagen": 2
  },
  {
    "dates": "2025-05-03",
    "values": 9.52,
    "n_waagen": 2
  },
  {
    "dates": "2025-05-04",
    "values": 9.3,
    "n_waagen": 2
  },
  {
    "dates": "2025-05-05",
    "values": 8.91,
    "n_waagen": 2
  },
  {
    "dates": "2025-05-06",
    "values": 8.89,
    "n_waagen": 2
  },
  {
    "dates": "2025-05-07",
    "values": 8.54,
    "n_waagen": 2
  },
  {
    "dates": "2025-05-08",
    "values": 8.33,
    "n_waagen": 2
  },
  {
    "dates": "2025-05-09",
    "values": 8.15,
    "n_waagen": 2
  },
  {
    "dates": "2025-05-10",
    "values": 8.94,
    "n_waagen": 2
  },
  {
    "dates": "2025-05-11",
    "values": 9.45,
    "n_waagen": 2
  },
  {
    "dates": "2025-05-12",
    "values": 9.88,
    "n_waagen": 2
  },
  {
    "dates": "2025-05-13",
    "values": 10.14,
    "n_waagen": 2
  },
  {
    "dates": "2025-05-14",
    "values": 10.71,
    "n_waagen": 2
  },
  {
    "dates": "2025-05-15",
    "values": 10.8,
    "n_waagen": 2
  },
  {
    "dates": "2025-05-16",
    "values": 10.81,
    "n_waagen": 2
  },
  {
    "dates": "2025-05-17",
    "values": 11.14,
    "n_waagen": 2
  },
  {
    "dates": "2025-05-18",
    "values": 11.09,
    "n_waagen": 2
  },
  {
    "dates": "2025-05-19",
    "values": 11.48,
    "n_waagen": 2
  },
  {
    "dates": "2025-05-20",
    "values": 11.69,
    "n_waagen": 2
  },
  {
    "dates": "2025-05-21",
    "values": 11.61,
    "n_waagen": 2
  },
  {
    "dates": "2025-05-22",
    "values": null,
    "n_waagen": null
  },
  {
    "dates": "2025-05-23",
    "values": 11.21,
    "n_waagen": 2
  },
  {
    "dates": "2025-05-24",
    "values": 10.97,
    "n_waagen": 2
  },
  {
    "dates": "2025-05-25",
    "values": 11.44,
    "n_waagen": 2
  },
  {
    "dates": "2025-05-26",
    "values": 11.12,
    "n_waagen": 2
  },
  {
    "dates": "2025-05-27",
    "values": 10.84,
    "n_waagen": 2
  },
  {
    "dates": "2025-05-28",
    "values": 10.8,
    "n_waagen": 2
  },
  {
    "dates": "2025-05-29",
    "values": 10.33,
    "n_waagen": 2
  },
  {
    "dates": "2025-05-30",
    "values": 10.0,
    "n_waagen": 2
  },
  {
    "dates": "2025-05-31",
    "values": 10.14,
    "n_waagen": 2
  },
  {
    "dates": "2025-06-01",
    "values": 10.38,
    "n_waagen": 2
  },
  {
    "dates": "2025-06-02",
    "values": 9.96,
    "n_waagen": 2
  },
  {
    "dates": "2025-06-03",
    "values": 9.98,
    "n_waagen": 2
  },
  {
    "dates": "2025-06-04",
    "values": 9.73,
    "n_waagen": 2
  },
  {
    "dates": "2025-06-05",
    "values": 9.56,
    "n_waagen": 2
  },
  {
    "dates": "2025-06-06",
    "values": 9.22,
    "n_waagen": 2
  },
  {
    "dates": "2025-06-07",
    "values": 8.57,
    "n_waagen": 2
  },
  {
    "dates": "2025-06-08",
    "values": 8.23,
    "n_waagen": 2
  },
  {
    "dates": "2025-06-09",
    "values": 8.78,
    "n_waagen": 2
  },
  {
    "dates": "2025-06-10",
    "values": 9.46,
    "n_waagen": 2
  },
  {
    "dates": "2025-06-11",
    "values": 10.38,
    "n_waagen": 2
  },
  {
    "dates": "2025-06-12",
    "values": 11.43,
    "n_waagen": 2
  },
  {
    "dates": "2025-06-13",
    "values": 12.46,
    "n_waagen": 2
  },
  {
    "dates": "2025-06-14",
    "values": 13.89,
    "n_waagen": 2
  },
  {
    "dates": "2025-06-15",
    "values": 13.61,
    "n_waagen": 2
  },
  {
    "dates": "2025-06-16",
    "values": 12.85,
    "n_waagen": 2
  },
  {
    "dates": "2025-06-17",
    "values": 13.73,
    "n_waagen": 2
  },
  {
    "dates": "2025-06-18",
    "values": 14.86,
    "n_waagen": 2
  },
  {
    "dates": "2025-06-19",
    "values": 15.86,
    "n_waagen": 2
  },
  {
    "dates": "2025-06-20",
    "values": 16.47,
    "n_waagen": 2
  },
  {
    "dates": "2025-06-21",
    "values": 17.05,
    "n_waagen": 2
  },
  {
    "dates": "2025-06-22",
    "values": 18.09,
    "n_waagen": 2
  },
  {
    "dates": "2025-06-23",
    "values": 18.11,
    "n_waagen": 2
  },
  {
    "dates": "2025-06-24",
    "values": 18.53,
    "n_waagen": 2
  },
  {
    "dates": "2025-06-25",
    "values": 19.56,
    "n_waagen": 2
  },
  {
    "dates": "2025-06-26",
    "values": 18.97,
    "n_waagen": 2
  },
  {
    "dates": "2025-06-27",
    "values": 18.44,
    "n_waagen": 2
  },
  {
    "dates": "2025-06-28",
    "values": 18.63,
    "n_waagen": 2
  },
  {
    "dates": "2025-06-29",
    "values": 19.1,
    "n_waagen": 2
  },
  {
    "dates": "2025-06-30",
    "values": 19.24,
    "n_waagen": 2
  },
  {
    "dates": "2025-07-01",
    "values": 19.56,
    "n_waagen": 2
  },
  {
    "dates": "2025-07-02",
    "values": 19.61,
    "n_waagen": 2
  },
  {
    "dates": "2025-07-03",
    "values": 19.23,
    "n_waagen": 2
  },
  {
    "dates": "2025-07-04",
    "values": 19.38,
    "n_waagen": 2
  },
  {
    "dates": "2025-07-05",
    "values": 19.53,
    "n_waagen": 2
  },
  {
    "dates": "2025-07-06",
    "values": 18.94,
    "n_waagen": 2
  },
  {
    "dates": "2025-07-07",
    "values": 18.78,
    "n_waagen": 2
  },
  {
    "dates": "2025-07-08",
    "values": 18.52,
    "n_waagen": 2
  },
  {
    "dates": "2025-07-09",
    "values": 18.32,
    "n_waagen": 2
  },
  {
    "dates": "2025-07-10",
    "values": 17.56,
    "n_waagen": 2
  },
  {
    "dates": "2025-07-11",
    "values": 17.27,
    "n_waagen": 2
  },
  {
    "dates": "2025-07-12",
    "values": 17.07,
    "n_waagen": 2
  },
  {
    "dates": "2025-07-13",
    "values": 16.75,
    "n_waagen": 2
  },
  {
    "dates": "2025-07-14",
    "values": 16.51,
    "n_waagen": 2
  },
  {
    "dates": "2025-07-15",
    "values": 16.15,
    "n_waagen": 2
  },
  {
    "dates": "2025-07-16",
    "values": 16.01,
    "n_waagen": 2
  },
  {
    "dates": "2025-07-17",
    "values": 15.6,
    "n_waagen": 2
  },
  {
    "dates": "2025-07-18",
    "values": 15.33,
    "n_waagen": 2
  },
  {
    "dates": "2025-07-19",
    "values": 15.32,
    "n_waagen": 2
  },
  {
    "dates": "2025-07-20",
    "values": 15.14,
    "n_waagen": 2
  },
  {
    "dates": "2025-07-21",
    "values": 15.06,
    "n_waagen": 2
  },
  {
    "dates": "2025-07-22",
    "values": 14.95,
    "n_waagen": 2
  },
  {
    "dates": "2025-07-23",
    "values": 15.03,
    "n_waagen": 2
  },
  {
    "dates": "2025-07-24",
    "values": 14.95,
    "n_waagen": 2
  },
  {
    "dates": "2025-07-25",
    "values": 14.78,
    "n_waagen": 2
  },
  {
    "dates": "2025-07-26",
    "values": 14.92,
    "n_waagen": 2
  },
  {
    "dates": "2025-07-27",
    "values": 14.64,
    "n_waagen": 2
  },
  {
    "dates": "2025-07-28",
    "values": 14.53,
    "n_waagen": 2
  },
  {
    "dates": "2025-07-29",
    "values": 14.34,
    "n_waagen": 2
  },
  {
    "dates": "2025-07-30",
    "values": 14.08,
    "n_waagen": 2
  },
  {
    "dates": "2025-07-31",
    "values": 13.91,
    "n_waagen": 2
  },
  {
    "dates": "2025-08-01",
    "values": 13.68,
    "n_waagen": 2
  },
  {
    "dates": "2025-08-02",
    "values": 13.39,
    "n_waagen": 2
  },
  {
    "dates": "2025-08-03",
    "values": 13.4,
    "n_waagen": 2
  },
  {
    "dates": "2025-08-04",
    "values": null,
    "n_waagen": null
  },
  {
    "dates": "2025-08-05",
    "values": null,
    "n_waagen": null
  },
  {
    "dates": "2025-08-06",
    "values": 12.97,
    "n_waagen": 2
  },
  {
    "dates": "2025-08-07",
    "values": 12.62,
    "n_waagen": 2
  },
  {
    "dates": "2025-08-08",
    "values": 12.33,
    "n_waagen": 2
  },
  {
    "dates": "2025-08-09",
    "values": 12.09,
    "n_waagen": 2
  },
  {
    "dates": "2025-08-10",
    "values": 11.85,
    "n_waagen": 2
  },
  {
    "dates": "2025-08-11",
    "values": 11.57,
    "n_waagen": 2
  },
  {
    "dates": "2025-08-12",
    "values": 11.52,
    "n_waagen": 2
  },
  {
    "dates": "2025-08-13",
    "values": null,
    "n_waagen": null
  },
  {
    "dates": "2025-08-14",
    "values": null,
    "n_waagen": null
  },
  {
    "dates": "2025-08-15",
    "values": 11.3,
    "n_waagen": 2
  },
  {
    "dates": "2025-08-16",
    "values": 11.15,
    "n_waagen": 2
  },
  {
    "dates": "2025-08-17",
    "values": 10.97,
    "n_waagen": 2
  },
  {
    "dates": "2025-08-18",
    "values": 10.73,
    "n_waagen": 2
  },
  {
    "dates": "2025-08-19",
    "values": 10.72,
    "n_waagen": 2
  },
  {
    "dates": "2025-08-20",
    "values": null,
    "n_waagen": null
  },
  {
    "dates": "2025-08-21",
    "values": null,
    "n_waagen": null
  },
  {
    "dates": "2025-08-22",
    "values": null,
    "n_waagen": null
  },
  {
    "dates": "2025-08-23",
    "values": null,
    "n_waagen": null
  },
  {
    "dates": "2025-08-24",
    "values": null,
    "n_waagen": null
  },
  {
    "dates": "2025-08-25",
    "values": null,
    "n_waagen": null
  },
  {
    "dates": "2025-08-26",
    "values": null,
    "n_waagen": null
  },
  {
    "dates": "2025-08-27",
    "values": null,
    "n_waagen": null
  },
  {
    "dates": "2025-08-28",
    "values": null,
    "n_waagen": null
  },
  {
    "dates": "2025-08-29",
    "values": null,
    "n_waagen": null
  },
  {
    "dates": "2025-08-30",
    "values": null,
    "n_waagen": null
  },
  {
    "dates": "2025-08-31",
    "values": null,
    "n_waagen": null
  }
]
