[{"dates":"2013-01-01","values":0.05,"n_waagen":85},{"dates":"2013-01-02","values":-0.03,"n_waagen":84},{"dates":"2013-01-03","values":0.07,"n_waagen":83},{"dates":"2013-01-04","values":0.06,"n_waagen":83},{"dates":"2013-01-05","values":-0.02,"n_waagen":81},{"dates":"2013-01-06","values":-0.06,"n_waagen":82},{"dates":"2013-01-07","values":-0.16,"n_waagen":85},{"dates":"2013-01-08","values":-0.19,"n_waagen":85},{"dates":"2013-01-09","values":-0.19,"n_waagen":85},{"dates":"2013-01-10","values":-0.19,"n_waagen":85},{"dates":"2013-01-11","values":-0.27,"n_waagen":86},{"dates":"2013-01-12","values":-0.21,"n_waagen":87},{"dates":"2013-01-13","values":-0.28,"n_waagen":83},{"dates":"2013-01-14","values":-0.35,"n_waagen":83},{"dates":"2013-01-15","values":-0.06,"n_waagen":82},{"dates":"2013-01-16","values":0.0,"n_waagen":83},{"dates":"2013-01-17","values":0.21,"n_waagen":83},{"dates":"2013-01-18","values":0.1,"n_waagen":83},{"dates":"2013-01-19","values":-0.05,"n_waagen":81},{"dates":"2013-01-20","values":0.6,"n_waagen":82},{"dates":"2013-01-21","values":1.0,"n_waagen":81},{"dates":"2013-01-22","values":1.08,"n_waagen":83},{"dates":"2013-01-23","values":0.94,"n_waagen":83},{"dates":"2013-01-24","values":0.82,"n_waagen":77},{"dates":"2013-01-25","values":0.72,"n_waagen":78},{"dates":"2013-01-26","values":0.67,"n_waagen":78},{"dates":"2013-01-27","values":0.4,"n_waagen":79},{"dates":"2013-01-28","values":-0.38,"n_waagen":78},{"dates":"2013-01-29","values":-0.49,"n_waagen":81},{"dates":"2013-01-30","values":-0.68,"n_waagen":81},{"dates":"2013-01-31","values":-0.89,"n_waagen":82},{"dates":"2013-02-01","values":-0.74,"n_waagen":73},{"dates":"2013-02-02","values":-0.85,"n_waagen":74},{"dates":"2013-02-03","values":-0.79,"n_waagen":76},{"dates":"2013-02-04","values":-0.74,"n_waagen":79},{"dates":"2013-02-05","values":-0.77,"n_waagen":81},{"dates":"2013-02-06","values":-0.7,"n_waagen":82},{"dates":"2013-02-07","values":-0.72,"n_waagen":81},{"dates":"2013-02-08","values":-0.7,"n_waagen":84},{"dates":"2013-02-09","values":-0.81,"n_waagen":87},{"dates":"2013-02-10","values":-0.96,"n_waagen":86},{"dates":"2013-02-11","values":-1.11,"n_waagen":85},{"dates":"2013-02-12","values":-1.14,"n_waagen":85},{"dates":"2013-02-13","values":-1.24,"n_waagen":84},{"dates":"2013-02-14","values":-1.2,"n_waagen":88},{"dates":"2013-02-15","values":-1.24,"n_waagen":88},{"dates":"2013-02-16","values":-1.37,"n_waagen":90},{"dates":"2013-02-17","values":-1.49,"n_waagen":93},{"dates":"2013-02-18","values":-1.61,"n_waagen":93},{"dates":"2013-02-19","values":-1.35,"n_waagen":90},{"dates":"2013-02-20","values":-1.54,"n_waagen":87},{"dates":"2013-02-21","values":-1.63,"n_waagen":91},{"dates":"2013-02-22","values":-1.67,"n_waagen":90},{"dates":"2013-02-23","values":-1.36,"n_waagen":90},{"dates":"2013-02-24","values":-1.29,"n_waagen":89},{"dates":"2013-02-25","values":-1.0,"n_waagen":88},{"dates":"2013-02-26","values":-1.55,"n_waagen":88},{"dates":"2013-02-27","values":-1.7,"n_waagen":89},{"dates":"2013-02-28","values":-1.82,"n_waagen":87},{"dates":"2013-03-01","values":-1.91,"n_waagen":89},{"dates":"2013-03-02","values":-2.1,"n_waagen":89},{"dates":"2013-03-03","values":-2.16,"n_waagen":91},{"dates":"2013-03-04","values":-2.47,"n_waagen":97},{"dates":"2013-03-05","values":-2.84,"n_waagen":95},{"dates":"2013-03-06","values":-3.11,"n_waagen":106},{"dates":"2013-03-07","values":-3.3,"n_waagen":110},{"dates":"2013-03-08","values":-3.38,"n_waagen":109},{"dates":"2013-03-09","values":-3.44,"n_waagen":110},{"dates":"2013-03-10","values":-3.37,"n_waagen":109},{"dates":"2013-03-11","values":-3.36,"n_waagen":108},{"dates":"2013-03-12","values":-2.33,"n_waagen":106},{"dates":"2013-03-13","values":-2.84,"n_waagen":106},{"dates":"2013-03-14","values":-3.11,"n_waagen":107},{"dates":"2013-03-15","values":-3.45,"n_waagen":108},{"dates":"2013-03-16","values":-3.76,"n_waagen":107},{"dates":"2013-03-17","values":-3.63,"n_waagen":108},{"dates":"2013-03-18","values":-3.75,"n_waagen":108},{"dates":"2013-03-19","values":-3.81,"n_waagen":107},{"dates":"2013-03-20","values":-3.65,"n_waagen":107},{"dates":"2013-03-21","values":-3.91,"n_waagen":108},{"dates":"2013-03-22","values":-4.1,"n_waagen":108},{"dates":"2013-03-23","values":-4.17,"n_waagen":108},{"dates":"2013-03-24","values":-4.3,"n_waagen":109},{"dates":"2013-03-25","values":-4.38,"n_waagen":107},{"dates":"2013-03-26","values":-4.44,"n_waagen":106},{"dates":"2013-03-27","values":-4.53,"n_waagen":107},{"dates":"2013-03-28","values":-4.61,"n_waagen":107},{"dates":"2013-03-29","values":-4.69,"n_waagen":108},{"dates":"2013-03-30","values":-4.76,"n_waagen":110},{"dates":"2013-03-31","values":-4.81,"n_waagen":111},{"dates":"2013-04-01","values":-4.93,"n_waagen":111},{"dates":"2013-04-02","values":-5.12,"n_waagen":111},{"dates":"2013-04-03","values":-5.2,"n_waagen":111},{"dates":"2013-04-04","values":-5.33,"n_waagen":113},{"dates":"2013-04-05","values":-5.38,"n_waagen":113},{"dates":"2013-04-06","values":-5.39,"n_waagen":112},{"dates":"2013-04-07","values":-5.56,"n_waagen":113},{"dates":"2013-04-08","values":-5.63,"n_waagen":113},{"dates":"2013-04-09","values":-5.55,"n_waagen":113},{"dates":"2013-04-10","values":-5.6,"n_waagen":113},{"dates":"2013-04-11","values":-5.56,"n_waagen":113},{"dates":"2013-04-12","values":-5.73,"n_waagen":112},{"dates":"2013-04-13","values":-5.86,"n_waagen":113},{"dates":"2013-04-14","values":-5.54,"n_waagen":113},{"dates":"2013-04-15","values":-5.02,"n_waagen":114},{"dates":"2013-04-16","values":-4.75,"n_waagen":114},{"dates":"2013-04-17","values":-4.1,"n_waagen":117},{"dates":"2013-04-18","values":-3.96,"n_waagen":117},{"dates":"2013-04-19","values":-4.06,"n_waagen":119},{"dates":"2013-04-20","values":-4.15,"n_waagen":118},{"dates":"2013-04-21","values":-4.13,"n_waagen":115},{"dates":"2013-04-22","values":-3.98,"n_waagen":115},{"dates":"2013-04-23","values":-3.71,"n_waagen":116},{"dates":"2013-04-24","values":-2.95,"n_waagen":115},{"dates":"2013-04-25","values":-2.19,"n_waagen":115},{"dates":"2013-04-26","values":-1.84,"n_waagen":114},{"dates":"2013-04-27","values":-2.05,"n_waagen":114},{"dates":"2013-04-28","values":-2.27,"n_waagen":111},{"dates":"2013-04-29","values":-2.46,"n_waagen":112},{"dates":"2013-04-30","values":-2.44,"n_waagen":110},{"dates":"2013-05-01","values":-2.28,"n_waagen":112},{"dates":"2013-05-02","values":-1.87,"n_waagen":115},{"dates":"2013-05-03","values":-1.42,"n_waagen":113},{"dates":"2013-05-04","values":-1.09,"n_waagen":114},{"dates":"2013-05-05","values":-0.17,"n_waagen":113},{"dates":"2013-05-06","values":0.86,"n_waagen":113},{"dates":"2013-05-07","values":0.95,"n_waagen":114},{"dates":"2013-05-08","values":1.84,"n_waagen":113},{"dates":"2013-05-09","values":2.49,"n_waagen":113},{"dates":"2013-05-10","values":2.4,"n_waagen":113},{"dates":"2013-05-11","values":2.43,"n_waagen":111},{"dates":"2013-05-12","values":2.2,"n_waagen":109},{"dates":"2013-05-13","values":2.13,"n_waagen":108},{"dates":"2013-05-14","values":2.45,"n_waagen":108},{"dates":"2013-05-15","values":3.75,"n_waagen":110},{"dates":"2013-05-16","values":4.6,"n_waagen":109},{"dates":"2013-05-17","values":4.82,"n_waagen":112},{"dates":"2013-05-18","values":5.59,"n_waagen":112},{"dates":"2013-05-19","values":6.81,"n_waagen":110},{"dates":"2013-05-20","values":6.39,"n_waagen":110},{"dates":"2013-05-21","values":6.38,"n_waagen":111},{"dates":"2013-05-22","values":5.95,"n_waagen":111},{"dates":"2013-05-23","values":5.85,"n_waagen":114},{"dates":"2013-05-24","values":5.56,"n_waagen":115},{"dates":"2013-05-25","values":5.46,"n_waagen":112},{"dates":"2013-05-26","values":5.34,"n_waagen":114},{"dates":"2013-05-27","values":5.77,"n_waagen":112},{"dates":"2013-05-28","values":7.34,"n_waagen":113},{"dates":"2013-05-29","values":6.98,"n_waagen":112},{"dates":"2013-05-30","values":7.0,"n_waagen":109},{"dates":"2013-05-31","values":6.82,"n_waagen":110},{"dates":"2013-06-01","values":6.64,"n_waagen":108},{"dates":"2013-06-02","values":6.88,"n_waagen":111},{"dates":"2013-06-03","values":7.3,"n_waagen":113},{"dates":"2013-06-04","values":8.5,"n_waagen":114},{"dates":"2013-06-05","values":10.33,"n_waagen":113},{"dates":"2013-06-06","values":11.92,"n_waagen":114},{"dates":"2013-06-07","values":13.67,"n_waagen":115},{"dates":"2013-06-08","values":14.97,"n_waagen":115},{"dates":"2013-06-09","values":14.89,"n_waagen":114},{"dates":"2013-06-10","values":14.83,"n_waagen":115},{"dates":"2013-06-11","values":15.6,"n_waagen":118},{"dates":"2013-06-12","values":16.46,"n_waagen":118},{"dates":"2013-06-13","values":17.57,"n_waagen":119},{"dates":"2013-06-14","values":17.1,"n_waagen":120},{"dates":"2013-06-15","values":17.32,"n_waagen":116},{"dates":"2013-06-16","values":18.03,"n_waagen":117},{"dates":"2013-06-17","values":19.75,"n_waagen":118},{"dates":"2013-06-18","values":21.39,"n_waagen":116},{"dates":"2013-06-19","values":22.79,"n_waagen":115},{"dates":"2013-06-20","values":23.21,"n_waagen":114},{"dates":"2013-06-21","values":22.52,"n_waagen":113},{"dates":"2013-06-22","values":22.53,"n_waagen":111},{"dates":"2013-06-23","values":22.25,"n_waagen":111},{"dates":"2013-06-24","values":22.11,"n_waagen":110},{"dates":"2013-06-25","values":21.84,"n_waagen":111},{"dates":"2013-06-26","values":21.59,"n_waagen":113},{"dates":"2013-06-27","values":21.58,"n_waagen":113},{"dates":"2013-06-28","values":21.33,"n_waagen":112},{"dates":"2013-06-29","values":21.17,"n_waagen":112},{"dates":"2013-06-30","values":21.13,"n_waagen":112},{"dates":"2013-07-01","values":22.09,"n_waagen":113},{"dates":"2013-07-02","values":23.32,"n_waagen":111},{"dates":"2013-07-03","values":23.67,"n_waagen":114},{"dates":"2013-07-04","values":24.21,"n_waagen":114},{"dates":"2013-07-05","values":25.26,"n_waagen":116},{"dates":"2013-07-06","values":26.54,"n_waagen":115},{"dates":"2013-07-07","values":27.81,"n_waagen":117},{"dates":"2013-07-08","values":29.07,"n_waagen":116},{"dates":"2013-07-09","values":30.35,"n_waagen":115},{"dates":"2013-07-10","values":31.08,"n_waagen":116},{"dates":"2013-07-11","values":31.05,"n_waagen":116},{"dates":"2013-07-12","values":31.82,"n_waagen":120},{"dates":"2013-07-13","values":32.8,"n_waagen":121},{"dates":"2013-07-14","values":33.98,"n_waagen":122},{"dates":"2013-07-15","values":35.05,"n_waagen":124},{"dates":"2013-07-16","values":36.21,"n_waagen":124},{"dates":"2013-07-17","values":37.17,"n_waagen":124},{"dates":"2013-07-18","values":37.98,"n_waagen":123},{"dates":"2013-07-19","values":38.55,"n_waagen":123},{"dates":"2013-07-20","values":39.08,"n_waagen":122},{"dates":"2013-07-21","values":39.56,"n_waagen":122},{"dates":"2013-07-22","values":40.0,"n_waagen":122},{"dates":"2013-07-23","values":40.3,"n_waagen":121},{"dates":"2013-07-24","values":40.51,"n_waagen":121},{"dates":"2013-07-25","values":40.7,"n_waagen":122},{"dates":"2013-07-26","values":40.8,"n_waagen":125},{"dates":"2013-07-27","values":40.73,"n_waagen":122},{"dates":"2013-07-28","values":40.75,"n_waagen":122},{"dates":"2013-07-29","values":40.69,"n_waagen":119},{"dates":"2013-07-30","values":40.34,"n_waagen":119},{"dates":"2013-07-31","values":40.08,"n_waagen":119},{"dates":"2013-08-01","values":39.89,"n_waagen":120},{"dates":"2013-08-02","values":39.6,"n_waagen":122},{"dates":"2013-08-03","values":39.59,"n_waagen":122},{"dates":"2013-08-04","values":39.47,"n_waagen":121},{"dates":"2013-08-05","values":39.29,"n_waagen":122},{"dates":"2013-08-06","values":39.21,"n_waagen":121},{"dates":"2013-08-07","values":39.06,"n_waagen":120},{"dates":"2013-08-08","values":38.94,"n_waagen":119},{"dates":"2013-08-09","values":38.75,"n_waagen":120},{"dates":"2013-08-10","values":38.46,"n_waagen":120},{"dates":"2013-08-11","values":38.25,"n_waagen":119},{"dates":"2013-08-12","values":38.16,"n_waagen":118},{"dates":"2013-08-13","values":37.97,"n_waagen":118},{"dates":"2013-08-14","values":37.75,"n_waagen":115},{"dates":"2013-08-15","values":37.47,"n_waagen":114},{"dates":"2013-08-16","values":37.18,"n_waagen":113},{"dates":"2013-08-17","values":37.03,"n_waagen":115},{"dates":"2013-08-18","values":37.05,"n_waagen":114},{"dates":"2013-08-19","values":36.99,"n_waagen":117},{"dates":"2013-08-20","values":36.7,"n_waagen":114},{"dates":"2013-08-21","values":36.46,"n_waagen":115},{"dates":"2013-08-22","values":36.24,"n_waagen":115},{"dates":"2013-08-23","values":36.08,"n_waagen":117},{"dates":"2013-08-24","values":36.16,"n_waagen":116},{"dates":"2013-08-25","values":36.21,"n_waagen":119},{"dates":"2013-08-26","values":36.04,"n_waagen":117},{"dates":"2013-08-27","values":35.79,"n_waagen":117},{"dates":"2013-08-28","values":35.48,"n_waagen":111},{"dates":"2013-08-29","values":35.21,"n_waagen":112},{"dates":"2013-08-30","values":35.04,"n_waagen":113},{"dates":"2013-08-31","values":34.92,"n_waagen":110},{"dates":"2013-09-01","values":34.71,"n_waagen":130},{"dates":"2013-09-02","values":34.53,"n_waagen":133},{"dates":"2013-09-03","values":34.38,"n_waagen":124},{"dates":"2013-09-04","values":34.2,"n_waagen":125},{"dates":"2013-09-05","values":34.03,"n_waagen":131},{"dates":"2013-09-06","values":33.9,"n_waagen":132},{"dates":"2013-09-07","values":33.88,"n_waagen":130},{"dates":"2013-09-08","values":33.96,"n_waagen":132},{"dates":"2013-09-09","values":33.9,"n_waagen":137},{"dates":"2013-09-10","values":33.84,"n_waagen":138},{"dates":"2013-09-11","values":33.81,"n_waagen":141},{"dates":"2013-09-12","values":33.67,"n_waagen":141},{"dates":"2013-09-13","values":33.42,"n_waagen":141},{"dates":"2013-09-14","values":33.47,"n_waagen":141},{"dates":"2013-09-15","values":33.34,"n_waagen":141},{"dates":"2013-09-16","values":33.28,"n_waagen":139},{"dates":"2013-09-17","values":33.16,"n_waagen":137},{"dates":"2013-09-18","values":33.17,"n_waagen":134},{"dates":"2013-09-19","values":32.97,"n_waagen":137},{"dates":"2013-09-20","values":32.91,"n_waagen":138},{"dates":"2013-09-21","values":32.6,"n_waagen":137},{"dates":"2013-09-22","values":32.46,"n_waagen":137},{"dates":"2013-09-23","values":32.3,"n_waagen":138},{"dates":"2013-09-24","values":32.21,"n_waagen":138},{"dates":"2013-09-25","values":32.14,"n_waagen":138},{"dates":"2013-09-26","values":32.07,"n_waagen":138},{"dates":"2013-09-27","values":31.91,"n_waagen":138},{"dates":"2013-09-28","values":31.78,"n_waagen":137},{"dates":"2013-09-29","values":31.65,"n_waagen":137},{"dates":"2013-09-30","values":31.55,"n_waagen":136},{"dates":"2013-10-01","values":31.38,"n_waagen":136},{"dates":"2013-10-02","values":31.21,"n_waagen":135},{"dates":"2013-10-03","values":31.05,"n_waagen":132},{"dates":"2013-10-04","values":31.09,"n_waagen":132},{"dates":"2013-10-05","values":31.34,"n_waagen":134},{"dates":"2013-10-06","values":31.25,"n_waagen":134},{"dates":"2013-10-07","values":31.09,"n_waagen":133},{"dates":"2013-10-08","values":31.01,"n_waagen":135},{"dates":"2013-10-09","values":31.04,"n_waagen":134},{"dates":"2013-10-10","values":31.04,"n_waagen":137},{"dates":"2013-10-11","values":31.09,"n_waagen":134},{"dates":"2013-10-12","values":31.03,"n_waagen":134},{"dates":"2013-10-13","values":30.92,"n_waagen":134},{"dates":"2013-10-14","values":30.96,"n_waagen":133},{"dates":"2013-10-15","values":30.93,"n_waagen":132},{"dates":"2013-10-16","values":30.85,"n_waagen":133},{"dates":"2013-10-17","values":30.83,"n_waagen":135},{"dates":"2013-10-18","values":30.69,"n_waagen":133},{"dates":"2013-10-19","values":30.58,"n_waagen":133},{"dates":"2013-10-20","values":30.62,"n_waagen":132},{"dates":"2013-10-21","values":30.49,"n_waagen":132},{"dates":"2013-10-22","values":30.4,"n_waagen":132},{"dates":"2013-10-23","values":30.4,"n_waagen":133},{"dates":"2013-10-24","values":30.32,"n_waagen":133},{"dates":"2013-10-25","values":30.36,"n_waagen":132},{"dates":"2013-10-26","values":30.26,"n_waagen":129},{"dates":"2013-10-27","values":30.23,"n_waagen":129},{"dates":"2013-10-28","values":30.09,"n_waagen":133},{"dates":"2013-10-29","values":29.99,"n_waagen":131},{"dates":"2013-10-30","values":29.94,"n_waagen":133},{"dates":"2013-10-31","values":29.9,"n_waagen":134},{"dates":"2013-11-01","values":29.96,"n_waagen":133},{"dates":"2013-11-02","values":30.05,"n_waagen":132},{"dates":"2013-11-03","values":30.01,"n_waagen":131},{"dates":"2013-11-04","values":30.04,"n_waagen":133},{"dates":"2013-11-05","values":30.08,"n_waagen":132},{"dates":"2013-11-06","values":30.09,"n_waagen":140},{"dates":"2013-11-07","values":30.0,"n_waagen":141},{"dates":"2013-11-08","values":30.03,"n_waagen":141},{"dates":"2013-11-09","values":29.88,"n_waagen":140},{"dates":"2013-11-10","values":29.92,"n_waagen":139},{"dates":"2013-11-11","values":29.81,"n_waagen":139},{"dates":"2013-11-12","values":29.84,"n_waagen":140},{"dates":"2013-11-13","values":29.76,"n_waagen":137},{"dates":"2013-11-14","values":29.76,"n_waagen":136},{"dates":"2013-11-15","values":29.69,"n_waagen":135},{"dates":"2013-11-16","values":29.66,"n_waagen":136},{"dates":"2013-11-17","values":29.64,"n_waagen":138},{"dates":"2013-11-18","values":29.59,"n_waagen":140},{"dates":"2013-11-19","values":29.7,"n_waagen":141},{"dates":"2013-11-20","values":29.72,"n_waagen":141},{"dates":"2013-11-21","values":29.75,"n_waagen":139},{"dates":"2013-11-22","values":29.6,"n_waagen":140},{"dates":"2013-11-23","values":29.59,"n_waagen":141},{"dates":"2013-11-24","values":29.54,"n_waagen":139},{"dates":"2013-11-25","values":29.51,"n_waagen":138},{"dates":"2013-11-26","values":29.48,"n_waagen":136},{"dates":"2013-11-27","values":29.48,"n_waagen":136},{"dates":"2013-11-28","values":29.5,"n_waagen":136},{"dates":"2013-11-29","values":29.7,"n_waagen":131},{"dates":"2013-11-30","values":29.7,"n_waagen":131},{"dates":"2013-12-01","values":29.65,"n_waagen":132},{"dates":"2013-12-02","values":29.54,"n_waagen":134},{"dates":"2013-12-03","values":29.51,"n_waagen":132},{"dates":"2013-12-04","values":29.54,"n_waagen":131},{"dates":"2013-12-05","values":29.64,"n_waagen":133},{"dates":"2013-12-06","values":29.73,"n_waagen":133},{"dates":"2013-12-07","values":29.76,"n_waagen":139},{"dates":"2013-12-08","values":29.58,"n_waagen":139},{"dates":"2013-12-09","values":29.11,"n_waagen":141},{"dates":"2013-12-10","values":28.92,"n_waagen":141},{"dates":"2013-12-11","values":28.92,"n_waagen":142},{"dates":"2013-12-12","values":28.89,"n_waagen":139},{"dates":"2013-12-13","values":28.86,"n_waagen":137},{"dates":"2013-12-14","values":29.0,"n_waagen":136},{"dates":"2013-12-15","values":28.89,"n_waagen":135},{"dates":"2013-12-16","values":28.75,"n_waagen":136},{"dates":"2013-12-17","values":28.66,"n_waagen":135},{"dates":"2013-12-18","values":28.61,"n_waagen":137},{"dates":"2013-12-19","values":28.67,"n_waagen":137},{"dates":"2013-12-20","values":28.61,"n_waagen":137},{"dates":"2013-12-21","values":28.54,"n_waagen":137},{"dates":"2013-12-22","values":28.6,"n_waagen":137},{"dates":"2013-12-23","values":28.47,"n_waagen":137},{"dates":"2013-12-24","values":28.35,"n_waagen":134},{"dates":"2013-12-25","values":28.37,"n_waagen":134},{"dates":"2013-12-26","values":28.42,"n_waagen":134},{"dates":"2013-12-27","values":28.28,"n_waagen":133},{"dates":"2013-12-28","values":28.38,"n_waagen":132},{"dates":"2013-12-29","values":28.28,"n_waagen":133},{"dates":"2013-12-30","values":28.19,"n_waagen":132},{"dates":"2013-12-31","values":28.14,"n_waagen":129}]